rscad/boolean/__init__.py
rscad/boolean/core.py
rscad/boolean/fun_tools.py
rscad/boolean/polydata.py
rscad/boolean/rboolean.cpython-310-x86_64-linux-gnu.so
rscad/concave/rconcave.cpython-310-x86_64-linux-gnu.so
rscad/draft/__init__.py
rscad/draft/core.py
rscad/draft/polydata.py
rscad/draft/rdraft.cpython-310-x86_64-linux-gnu.so
rscad/hello/__init__.py
rscad/hello/rhello.cpython-310-x86_64-linux-gnu.so
rscad-0.0.6.dist-info/LICENSE
rscad-0.0.6.dist-info/METADATA
rscad-0.0.6.dist-info/WHEEL
rscad-0.0.6.dist-info/top_level.txt
rscad-0.0.6.dist-info/RECORD
