Metadata-Version: 2.1
Name: rscad
Version: 0.0.6
Summary: rusty cad utils
Author: Glenn
Author-email: gward@python.net
License-File: LICENSE
Requires-Dist: pyvista
Requires-Dist: numpy
